epigos/__init__.py
epigos/__version__.py
epigos/client.py
epigos/core/__init__.py
epigos/core/base.py
epigos/core/classification.py
epigos/core/object_detection.py
epigos/core/project.py
epigos/core/uploader.py
epigos/data_classes/__init__.py
epigos/data_classes/dataset.py
epigos/data_classes/prediction.py
epigos/data_classes/project.py
epigos/dataset/__init__.py
epigos/dataset/core.py
epigos/dataset/utils.py
epigos/exceptions.py
epigos/typings.py
epigos/utils/__init__.py
epigos/utils/image.py
epigos-2.1.0.dist-info/LICENSE
epigos-2.1.0.dist-info/METADATA
epigos-2.1.0.dist-info/WHEEL
epigos-2.1.0.dist-info/RECORD
