Metadata-Version: 2.1
Name: epigos
Version: 2.1.0
Summary: Epigos AI Python SDK
Home-page: https://github.com/Epigos-AI/epigos-python
License: MIT
Author: Philip Adzanoukpe
Author-email: philip@epigos.ai
Requires-Python: >=3.9,<4.0
Classifier: License :: OSI Approved :: MIT License
Classifier: Programming Language :: Python :: 3
Classifier: Programming Language :: Python :: 3.9
Classifier: Programming Language :: Python :: 3.10
Classifier: Programming Language :: Python :: 3.11
Classifier: Programming Language :: Python :: 3.12
Requires-Dist: httpx (>=0.24.1,<0.28.0)
Requires-Dist: imagesize (>=1.4.1,<2.0.0)
Requires-Dist: pillow (>=10.0.0,<11.0.0)
Requires-Dist: pybboxes (>=0.1.6,<0.2.0)
Requires-Dist: pyyaml (>=6.0.1,<7.0.0)
Requires-Dist: tenacity (>=8.3.0,<9.0.0)
Requires-Dist: tqdm (>=4.66.2,<5.0.0)
Requires-Dist: typing-extensions (>=4.7.1,<5.0.0)
Project-URL: Documentation, https://docs.epigos.ai/sdks/python
